calr/__init__.py
calr/_modidx.py
calr/core.py
calr-0.0.11.dist-info/LICENSE
calr-0.0.11.dist-info/METADATA
calr-0.0.11.dist-info/WHEEL
calr-0.0.11.dist-info/entry_points.txt
calr-0.0.11.dist-info/top_level.txt
calr-0.0.11.dist-info/RECORD
